kanasim/__init__.py
kanasim/kanasim.py
kanasim/py.typed
kanasim/data/biphone/distance_consonants_bi.csv
kanasim/data/biphone/distance_vowels_bi.csv
kanasim/data/biphone/kana2phonome_bi.csv
kanasim/data/biphone/kana_to_phonome_distance.csv
kanasim-0.0.2.dist-info/METADATA
kanasim-0.0.2.dist-info/WHEEL
kanasim-0.0.2.dist-info/licenses/LICENSE
kanasim-0.0.2.dist-info/RECORD
