Metadata-Version: 2.3
Name: kanasim
Version: 0.0.2
Summary: Calculator of phonetic similarity (distance) between Japanese kana characters
Project-URL: Homepage, https://github.com/jiroshimaya/kanasim
Author: shimajiroxyz
License:                                  Apache License
License-File: LICENSE
Keywords: distance,kana,phonome,similarity
Classifier: License :: OSI Approved :: Apache Software License
Classifier: Operating System :: OS Independent
Classifier: Programming Language :: Python :: 3.11
Requires-Python: >=3.11
Requires-Dist: jamorasep>=0.0.1
